{"event":[{"query":{"id":[{"timestamp_usec":"1151654940017338"},{"timestamp_usec":"1151654951367044"},{"timestamp_usec":"1151654953849175"},{"timestamp_usec":"1151654955679736"},{"timestamp_usec":"1151654957716310"},{"timestamp_usec":"1151654960062000"},{"timestamp_usec":"1151654962207242"},{"timestamp_usec":"1151654964239470"},{"timestamp_usec":"1151654966039794"}],"query_text":"dildo"}},{"query":{"id":[{"timestamp_usec":"1151654934096542"}],"query_text":"masturbation"}},{"query":{"id":[{"timestamp_usec":"1151654907468105"},{"timestamp_usec":"1151654921758516"},{"timestamp_usec":"1151654926271253"}],"query_text":"vagina"}},{"query":{"id":[{"timestamp_usec":"1151654806009276"},{"timestamp_usec":"1151654820137475"},{"timestamp_usec":"1151654822720145"},{"timestamp_usec":"1151654867478609"},{"timestamp_usec":"1151654874852542"},{"timestamp_usec":"1151654885453769"},{"timestamp_usec":"1151654888490636"},{"timestamp_usec":"1151654898232952"}],"query_text":"hot ass"}},{"query":{"id":[{"timestamp_usec":"1151654786926760"},{"timestamp_usec":"1151654796648141"},{"timestamp_usec":"1151654800648302"}],"query_text":"tight jeans"}},{"query":{"id":[{"timestamp_usec":"1151654711514779"},{"timestamp_usec":"1151654736409238"},{"timestamp_usec":"1151654743424270"},{"timestamp_usec":"1151654749165328"},{"timestamp_usec":"1151654754339760"},{"timestamp_usec":"1151654757842798"},{"timestamp_usec":"1151654766888908"},{"timestamp_usec":"1151654778296634"}],"query_text":"hot girls"}},{"query":{"id":[{"timestamp_usec":"1151654618972917"},{"timestamp_usec":"1151654650776052"},{"timestamp_usec":"1151654654362843"}],"query_text":"butts"}},{"query":{"id":[{"timestamp_usec":"1151461230475000"}],"query_text":"stripping"}},{"query":{"id":[{"timestamp_usec":"1151461224690000"}],"query_text":"masturbate"}},{"query":{"id":[{"timestamp_usec":"1151461216190000"}],"query_text":"butt"}},{"query":{"id":[{"timestamp_usec":"1151461211324000"}],"query_text":"sex"}},{"query":{"id":[{"timestamp_usec":"1151461195274000"}],"query_text":"pussy"}},{"query":{"id":[{"timestamp_usec":"1151461189489002"}],"query_text":"penis"}},{"query":{"id":[{"timestamp_usec":"1151265956964000"}],"query_text":"Supra"}},{"query":{"id":[{"timestamp_usec":"1151265953287000"}],"query_text":"GT47"}},{"query":{"id":[{"timestamp_usec":"1151265941400000"}],"query_text":"T88"}},{"query":{"id":[{"timestamp_usec":"1151265937536000"}],"query_text":"GT47"}},{"query":{"id":[{"timestamp_usec":"1151265800457000"}],"query_text":"GT42r"}},{"query":{"id":[{"timestamp_usec":"1151265768938000"}],"query_text":"GT40r"}},{"query":{"id":[{"timestamp_usec":"1151265295842000"}],"query_text":"GT35r"}},{"query":{"id":[{"timestamp_usec":"1151264934477000"},{"timestamp_usec":"1151265151819000"},{"timestamp_usec":"1151265208106000"},{"timestamp_usec":"1151265231511000"},{"timestamp_usec":"1151265257755000"},{"timestamp_usec":"1151265289917000"}],"query_text":"WRX"}},{"query":{"id":[{"timestamp_usec":"1151264828511547"},{"timestamp_usec":"1151264851369720"},{"timestamp_usec":"1151264859631442"},{"timestamp_usec":"1151264862917298"},{"timestamp_usec":"1151264876148372"},{"timestamp_usec":"1151264879537389"},{"timestamp_usec":"1151264881962849"},{"timestamp_usec":"1151264884803454"}],"query_text":"Fat man"}},{"query":{"id":[{"timestamp_usec":"1150927304548241"}],"query_text":"intel E6600"}},{"query":{"id":[{"timestamp_usec":"1149899758740000"}],"query_text":"WCG"}},{"query":{"id":[{"timestamp_usec":"1149035761321917"},{"timestamp_usec":"1149035856986846"},{"timestamp_usec":"1149035868369036"},{"timestamp_usec":"1149035868889088"},{"timestamp_usec":"1149035876575410"},{"timestamp_usec":"1149035880106203"}],"query_text":"pomeranian"}},{"query":{"id":[{"timestamp_usec":"1148004811233239"}],"query_text":"dragonball z"}},{"query":{"id":[{"timestamp_usec":"1147739651159176"}],"query_text":"rebar"}},{"query":{"id":[{"timestamp_usec":"1147739335818388"},{"timestamp_usec":"1147739442700515"}],"query_text":"world trade center"}},{"query":{"id":[{"timestamp_usec":"1147738669539175"}],"query_text":"question mark"}}]}